gpmicrobiome/__init__.py
gpmicrobiome/constants.py
gpmicrobiome/inference.py
gpmicrobiome/models.py
gpmicrobiome/utils.py
gpmicrobiome-1.1.0.dist-info/LICENSE
gpmicrobiome-1.1.0.dist-info/METADATA
gpmicrobiome-1.1.0.dist-info/WHEEL
gpmicrobiome-1.1.0.dist-info/entry_points.txt
gpmicrobiome-1.1.0.dist-info/RECORD
